tools/__init__.py
tools/md2excel.py
tools/qwen_content_search.py
qnvip_tools_sets_mcp-0.0.1.dist-info/METADATA
qnvip_tools_sets_mcp-0.0.1.dist-info/WHEEL
qnvip_tools_sets_mcp-0.0.1.dist-info/entry_points.txt
qnvip_tools_sets_mcp-0.0.1.dist-info/top_level.txt
qnvip_tools_sets_mcp-0.0.1.dist-info/RECORD
